{"description": "", "tags": [], "size": {"height": 480, "width": 640}, "objects": [{"description": "", "bitmap": null, "tags": [], "classTitle": "plates", "points": {"exterior": [[59, 80], [296, 7], [466, 5], [556, 6], [597, 93], [537, 117], [398, 165], [264, 215], [125, 259]], "interior": []}}, {"description": "", "bitmap": null, "tags": [], "classTitle": "intersection", "points": {"exterior": [[122, 248], [126, 260], [135, 257], [166, 229], [211, 196], [270, 157], [265, 183], [255, 216], [269, 211], [275, 183], [289, 144], [354, 110], [413, 83], [462, 92], [510, 105], [529, 111], [541, 94], [504, 87], [461, 76], [439, 71], [498, 52], [566, 28], [560, 14], [532, 22], [440, 53], [399, 69], [336, 102], [278, 132], [232, 163], [176, 207]], "interior": []}}]}